wav4py/__init__.py
wav4py-0.0.1.dist-info/licenses/LICENSE
wav4py-0.0.1.dist-info/WHEEL
wav4py-0.0.1.dist-info/METADATA
wav4py-0.0.1.dist-info/RECORD
